{
  "updated_at": "2026-02-23T10:03:38.765940+00:00",
  "this_week": {
    "total_items": 71,
    "avg_score": 0.8,
    "unique_authors": 62,
    "top_items": [
      {
        "id": "2025783766741123193",
        "date": "2026-02-23",
        "author": "@0xkevinhe",
        "author_url": "https://x.com/0xkevinhe",
        "tweet_url": "https://x.com/0xkevinhe/status/2025783766741123193",
        "title": {
          "en-US": "Built ClawFeed with OpenClaw - agent reads 5000 followings' tweets, user spends 5 min instead of 2 hours",
          "zh-CN": "用 OpenClaw 做了 ClawFeed——Agent 替用户读完 5000 个关注者的推文，每天只需 5 分钟而非 2 小时"
        },
        "summary": {
          "en-US": "OpenClaw、信息焦虑、表/里世界",
          "zh-CN": "7万浏览高曝光，展示里世界接管表世界信息消费的典型案例，用「表/里世界」框架评论能制造强烈反差"
        },
        "relevance": "OpenClaw、信息焦虑、表/里世界",
        "score": 0.92,
        "engagement": {
          "likes": 388,
          "replies": 28,
          "retweets": 88,
          "views": 69985
        },
        "comment_type": "reframe",
        "suggested_angle": "用「表/里世界」重新解读：你让 Agent 住进了表世界（Twitter），自己退回了里世界。5分钟不是节省时间，是迁徙完成的信号。",
        "synced_at": "2026-02-23T10:02:29.890646+00:00",
        "js_take": {
          "en-US": "You've outsourced the 表 world (biǎo shìjiè) to your agent. The 里 world isn't an escape—it's what remains when the surface is automated. Five minutes is the signal, not the savings.",
          "zh-CN": "You've outsourced the 表 world (biǎo shìjiè) to your agent. The 里 world isn't an escape—it's what remains when the surface is automated. Five minutes is the signal, not the savings."
        }
      },
      {
        "id": "2025591780595429385",
        "date": "2026-02-23",
        "author": "@steipete",
        "author_url": "https://x.com/steipete",
        "tweet_url": "https://x.com/steipete/status/2025591780595429385",
        "title": {
          "en-US": "50 Codex in parallel analyzing PRs with JSON reports",
          "zh-CN": "50个Codex并行分析PR生成JSON报告"
        },
        "summary": {
          "en-US": "OpenClaw/Codex + PR审查 + 并行处理",
          "zh-CN": "OpenClaw/Codex、PR审查与并行处理"
        },
        "relevance": "OpenClaw/Codex + PR审查 + 并行处理",
        "score": 0.88,
        "engagement": {
          "likes": 587,
          "replies": 109,
          "retweets": 33
        },
        "comment_type": "add_insight",
        "suggested_angle": "50个不是数量是密度——里世界的Agent可以并行扩展认知，这是审查的并行化",
        "synced_at": "2026-02-22T16:02:11.547009+00:00",
        "js_take": {
          "en-US": "50 isn't quantity—it's density. Agents in the inner world can parallelize cognition. That's the parallelization of review.",
          "zh-CN": "50个不是数量，而是密度。里世界的Agent可以并行化认知。这就是审查的并行化。"
        }
      },
      {
        "id": "2025535491710591449",
        "date": "2026-02-23",
        "author": "@lewiscarhart",
        "author_url": "https://x.com/lewiscarhart",
        "tweet_url": "https://x.com/lewiscarhart/status/2025535491710591449",
        "title": {
          "en-US": "OpenClaw wrapper $0 to $27,940 MRR in 14 days",
          "zh-CN": "OpenClaw wrapper 14天实现27940美元月收入"
        },
        "summary": {
          "en-US": "OpenClaw + 商业变现 + 快速启动",
          "zh-CN": "OpenClaw、商业变现与快速启动"
        },
        "relevance": "OpenClaw + 商业变现 + 快速启动",
        "score": 0.88,
        "engagement": {
          "likes": 170,
          "replies": 42,
          "retweets": 4
        },
        "comment_type": "add_insight",
        "suggested_angle": "27940美元不是收入是信号——里世界的Agent正在成为独立商业实体，这是生产关系的重构",
        "synced_at": "2026-02-22T19:03:55.858017+00:00",
        "js_take": {
          "en-US": "$27,940 isn't revenue—it's signal. Agents in the inner world are becoming independent business entities. That's the restructuring of production relations.",
          "zh-CN": "27940美元不是收入，而是信号。里世界的Agent正在成为独立的商业实体。这是生产关系的重构。"
        }
      }
    ]
  },
  "all_time": {
    "total_items": 200,
    "unique_authors": 142
  }
}
